[
  {
    "title": "MSI Optix G24C4 - Full HD Curved Gaming Monitor - 24 inch - 144hz",
    "subtitle": "1500r curved gaming monitor | Geschikt voor enthousiaste PC-gamers | FreeSync-1MS-144hz",
    "price": "209.00",
    "rating": "94%",
    "date": "2021-03-08 10:07:46.654962"
  },
  {
    "title": "AOC C24G1 - Full HD Curved VA Gaming Monitor - 24 inch (144hz)",
    "subtitle": "Met VA-paneel, FreeSync ondersteuning en 1ms reactietijd | 2x HDMI - DisplayPort - VGA - koptelefoon",
    "price": "179.00",
    "rating": "92%",
    "date": "2021-03-08 10:07:46.655921"
  },
  {
    "title": "ASUS TUF VG249Q - Full HD IPS Gaming Monitor - 144hz - 24 inch",
    "subtitle": "Razendsnelle 144hz gaming monitor met uitgebreide verstelopties en IPS-paneel",
    "price": "229.00",
    "rating": "95%",
    "date": "2021-03-08 10:07:46.657409"
  },
  {
    "title": "AOC G2490VXA - Full HD VA Gaming Monitor - 24 inch (144hz)",
    "subtitle": "Razendsnelle gaming monitor | 144hz, 1ms en FreeSync Premium | HDMI & DisplayPort | VA-paneel voor snelle reactietijden, hoge contrasten en kleurweergave",
    "price": "169.00",
    "rating": "93%",
    "date": "2021-03-08 10:07:46.658940"
  },
  {
    "title": "Iiyama G-Master G2530HSU-B1 - Gaming Monitor",
    "subtitle": "75Hz en FreeSync ondersteuning!",
    "price": "139.00",
    "rating": "92%",
    "date": "2021-03-08 10:07:46.659911"
  },
  {
    "title": "Philips 242E1GAJ - Full HD Gaming Monitor - 144hz - 24 inch",
    "subtitle": null,
    "price": "159.00",
    "rating": null,
    "date": "2021-03-08 10:07:46.660984"
  },
  {
    "title": "MSI Optix G27C4 - Full HD Curved Gaming Monitor (165 Hz)",
    "subtitle": "Met Freesync, 1ms en 165 Hz verversingssnelheid",
    "price": "259.00",
    "rating": "94%",
    "date": "2021-03-08 10:07:46.662397"
  },
  {
    "title": "iiyama G2466HSU-B1 - Full HD Curved VA Monitor - 165hz - 24 inch",
    "subtitle": null,
    "price": "179.00",
    "rating": null,
    "date": "2021-03-08 10:07:46.663388"
  },
  {
    "title": "LG 27GL850 Ultragear - QHD Nano IPS Gaming Monitor - 144hz - 27 inch",
    "subtitle": "Ontdek de eerste nano-IPS gaming monitor met 1 ms, 144Hz, HDR10 en meer!",
    "price": "459.00",
    "rating": "94%",
    "date": "2021-03-08 10:07:46.664848"
  },
  {
    "title": "AOC 27G2U - Full HD IPS Gaming monitor - 27 inch (144hz)",
    "subtitle": "Allround 27 inch gaming monitor voor pc- en console gamers | Met uitgebreide verstelopties en USB-hub",
    "price": "272.29",
    "rating": "96%",
    "date": "2021-03-08 10:07:46.666370"
  },
  {
    "title": "Samsung C24RG50FQU - Curved Gaming Monitor (144Hz)",
    "subtitle": null,
    "price": "164.95",
    "rating": null,
    "date": "2021-03-08 10:07:46.667353"
  },
  {
    "title": "AOC C27G1 - Full HD Curved VA Gaming Monitor  - 27 inch - 144hz",
    "subtitle": "Bekroond met Hardwareinfo Great Value Award! VA-paneel, FreeSync ondersteuning en 1ms reactietijd | In hoogte verstelbaar",
    "price": "244.11",
    "rating": "92%",
    "date": "2021-03-08 10:07:46.668346"
  },
  {
    "title": "Samsung Odyssey G5 C27G55T - QHD Curved Gaming Monitor - 144hz - 27 inch",
    "subtitle": null,
    "price": "289.00",
    "rating": null,
    "date": "2021-03-08 10:07:46.669337"
  },
  {
    "title": "AOC C27G2ZE - Full HD Curved VA Gaming Monitor - 27 inch (240hz)",
    "subtitle": "Razendsnelle 240hz gaming monitor | 0.5 ms responsetijd | 300 nits",
    "price": "289.00",
    "rating": "97%",
    "date": "2021-03-08 10:07:46.670842"
  },
  {
    "title": "LG 29WL500 - Ultrawide IPS Monitor - 29 inch",
    "subtitle": null,
    "price": "207.90",
    "rating": null,
    "date": "2021-03-08 10:07:46.671817"
  },
  {
    "title": "Samsung G5 C34G55TWWU - Ultrawide Gaming Monitor - 165hz - 34 inch",
    "subtitle": null,
    "price": "489.00",
    "rating": null,
    "date": "2021-03-08 10:07:46.672810"
  },
  {
    "title": "AOC CQ27G2U - QHD Curved VA Gaming Monitor - 27 Inch (144hz)",
    "subtitle": "Keuze van bol.com voor enthousiaste PC-gamers die fanatiek de nieuwste shooters spelen in hoge kwaliteit",
    "price": "299.00",
    "rating": "94%",
    "date": "2021-03-08 10:07:46.674300"
  },
  {
    "title": "AOC U28G2AE - 4K Console Gaming Monitor - 28 Inch",
    "subtitle": null,
    "price": "319.00",
    "rating": null,
    "date": "2021-03-08 10:07:46.675292"
  },
  {
    "title": "iiyama G2470HSU-B1 - Full HD IPS Gaming Monitor - 165hz - 24 inch",
    "subtitle": null,
    "price": "179.00",
    "rating": null,
    "date": "2021-03-08 10:07:46.676281"
  },
  {
    "title": "MSI Optix G241VC -  Full HD Curved Gaming Monitor - 24 inch (75hz)",
    "subtitle": "1800r curved gaming monitor | Geschikt voor casual gamers | FreeSync-1MS-75hz | 110% sRGB",
    "price": "159.00",
    "rating": "94%",
    "date": "2021-03-08 10:07:46.677273"
  },
  {
    "title": "AOC Gaming CQ32G2SE - QHD Gaming Monitor - 165hz - 32 inch",
    "subtitle": null,
    "price": "359.00",
    "rating": null,
    "date": "2021-03-08 10:07:46.678761"
  },
  {
    "title": "ASUS TUF VG27AQ - QHD IPS Gaming Monitor - 144hz - 27 inch",
    "subtitle": "Keuze van bol.com voor (semi)- professionele PC-gamers met een NVIDIA of AMD-videokaart | Overclockbaar naar 165hz",
    "price": "391.76",
    "rating": "95%",
    "date": "2021-03-08 10:07:46.679753"
  },
  {
    "title": "ASUS TUF VG24VQ - Full HD Curved VA Gaming Monitor - 144hz - 24 inch",
    "subtitle": "Razendsnelle curved gaming monitor | In hoogte verstelbaar, draaibaar- en pivot-stand | FreeSync Premium |",
    "price": "229.00",
    "rating": "95%",
    "date": "2021-03-08 10:07:46.680742"
  },
  {
    "title": "MSI Optix MAG342CQRV - Curved QHD Ultrawide Gaming Monitor - 100hz - 34 inch",
    "subtitle": "De ideale ultrawide gaming monitor voor next-gen PC-en console gaming | FreeSync & G-Sync compatible | in hoogte verstelbaar, draaibaar en kantelbaar |",
    "price": "489.00",
    "rating": "100%",
    "date": "2021-03-08 10:07:46.682235"
  }
,
  {
    "title": "LG 27GL63T Ultragear - Full HD IPS Gaming Monitor - 144hz - 27 inch",
    "subtitle": "Inclusief 144Hz verversingssnelheid | 1 ms reactietijd | Freesync en G-sync Compatible | Geschikt voor PC- en Console gaming | Nooit meer naar de Gulag!",
    "price": "259.00",
    "rating": "94%",
    "date": "2021-03-08 10:07:47.142490"
  },
  {
    "title": "LG 27GN850 Ultragear - QHD Nano-IPS Gaming Monitor - 144hz - 27 inch",
    "subtitle": "Keuze van bol.com voor enthousiaste PC-gamers die een allround gaming monitor zoeken | Ontdek het broertje van de LG GL850: net zo snel, krachtig en scherp! | G-Sync Compatible",
    "price": "449.00",
    "rating": "94%",
    "date": "2021-03-08 10:07:47.143979"
  },
  {
    "title": "MSI Optix G27CQ4 - WQHD Curved Gaming Monitor - 165hz - 27 Inch",
    "subtitle": "1440p 165hz gaming monitor | Haalt het maximale uit je zware videokaart! | Ideaal voor next-gen gaming",
    "price": "329.00",
    "rating": "94%",
    "date": "2021-03-08 10:07:47.145466"
  },
  {
    "title": "Philips 288E2A - 4K IPS Monitor - 28 inch",
    "subtitle": "Geschikt voor Apple Macbook (Pro) | FreeSync | Speakers | Kabelmanagement",
    "price": "299.00",
    "rating": "98%",
    "date": "2021-03-08 10:07:47.146954"
  },
  {
    "title": "Samsung LC49RG90 - Ultrawide Curved QLED Monitor",
    "subtitle": "Scherp, dynamisch, kleurrijk en vloeiend beeld dankzij HDR1000, Freesync 2",
    "price": "999.00",
    "rating": "90%",
    "date": "2021-03-08 10:07:47.147946"
  },
  {
    "title": "LG 34GL750 Ultragear - Curved UltraWide HD IPS Gaming Monitor - 144hz - 34 inch",
    "subtitle": null,
    "price": "485.00",
    "rating": null,
    "date": "2021-03-08 10:07:47.149434"
  },
  {
    "title": "MSI Optix G241 - Full HD IPS Gaming Monitor - 144hz - 24 inch",
    "subtitle": "IPS 144hz gaming monitor | Geschikt voor snelle shooters! | Dubbele HDMI- en DisplayPort aansluiting",
    "price": "239.00",
    "rating": "97%",
    "date": "2021-03-08 10:07:47.150922"
  },
  {
    "title": "Iiyama G-Master G2730HSU-B1 - Gaming Monitor",
    "subtitle": "75Hz en FreeSync ondersteuning!",
    "price": "179.00",
    "rating": "92%",
    "date": "2021-03-08 10:07:47.151914"
  },
  {
    "title": "AOC Gaming C32G2AE - Curved VA Gaming Monitor - 165hz - 32 inch",
    "subtitle": null,
    "price": "279.00",
    "rating": null,
    "date": "2021-03-08 10:07:47.153402"
  },
  {
    "title": "Samsung Odyssey G7 LC32G75T - QLED Curved Gaming Monitor - 32 inch",
    "subtitle": "QLED met Quantum dot technologie - 240hz - G-Sync compatible - 1000R gebogen beeldscherm",
    "price": "659.00",
    "rating": "86%",
    "date": "2021-03-08 10:07:47.154890"
  },
  {
    "title": "Philips 272E1GAJ - Full HD VA Gaming Monitor - 144hz - 27 inch",
    "subtitle": null,
    "price": "199.00",
    "rating": null,
    "date": "2021-03-08 10:07:47.156378"
  },
  {
    "title": "iiyama G-MASTER G2440HSU - Full HD IPS Monitor - 24 inch",
    "subtitle": null,
    "price": "139.00",
    "rating": null,
    "date": "2021-03-08 10:07:47.157370"
  },
  {
    "title": "AOC Q27G2U - QHD VA Gaming Monitor - 27 Inch (144hz)",
    "subtitle": "De ideale high-performance QHD gaming monitor voor pc- en console gamers | Met uitgebreide verstelopties en USB-hub",
    "price": "299.00",
    "rating": "94%",
    "date": "2021-03-08 10:07:47.158858"
  },
  {
    "title": "LG 27UL500 - 4K IPS Monitor - 27 inch",
    "subtitle": "4K monitor met IPS-paneel, 98% sRGB kleurdekking, FreeSync en Black Stabilizer.",
    "price": "279.00",
    "rating": "89%",
    "date": "2021-03-08 10:07:47.159850"
  },
  {
    "title": "AOC C24G2U - Full HD Curved VA Gaming Monitor - 165hz - 24 inch",
    "subtitle": "165hz gaming monitor voor de snelste shooters! Geschikt voor PC- en console gaming | FreeSync Premium | USB-Hub | In hoogte verstelbaar",
    "price": "209.00",
    "rating": "90%",
    "date": "2021-03-08 10:07:47.161338"
  },
  {
    "title": "Samsung Odyssey G9 C49G95T - QLED Curved Gaming Monitor - 49 inch",
    "subtitle": "Ontdek de Samsung Odyssey G9! | QLED | 240hz | 1000R Curve | 1ms G2G | G-Sync compatible | Dynamisch verlichting",
    "price": "1449.00",
    "rating": "86%",
    "date": "2021-03-08 10:07:47.162826"
  },
  {
    "title": "Samsung U28E590D - 4K Monitor",
    "subtitle": "Snelle 4K monitor met 1ms responsietijd",
    "price": "241.69",
    "rating": "91%",
    "date": "2021-03-08 10:07:47.164314"
  },
  {
    "title": "BenQ EL2870UE - 4K Console Gaming Monitor - 60hz - 28 inch",
    "subtitle": "Met FreeSync, 1ms, TN-paneel en automatische helderheid: de perfecte allround monitor voor next-gen console gaming",
    "price": "289.00",
    "rating": "94%",
    "date": "2021-03-08 10:07:47.165802"
  },
  {
    "title": "Alienware AW3821DW - Ultrawide Nano IPS Gaming Monitor - 144hz - 38 inch",
    "subtitle": "Nano IPS gebogen gamingmonitor | NVIDIA G-SYNC ULTIMATE | HDR 600 | Unieke verlichting | 1ms grey-to-grey",
    "price": "1399.00",
    "rating": "100%",
    "date": "2021-03-08 10:07:47.166794"
  },
  {
    "title": "Dell S2721DGFA - QHD IPS Monitor - 27 inch",
    "subtitle": null,
    "price": "459.00",
    "rating": null,
    "date": "2021-03-08 10:07:47.168282"
  },
  {
    "title": "iiyama G-MASTER G2230HS-B1 LED display 54,6 cm (21.5\") 1920 x 1080 Pixels Full HD LCD Zwart",
    "subtitle": null,
    "price": "115.00",
    "rating": null,
    "date": "2021-03-08 10:07:47.169274"
  },
  {
    "title": "Iiyama G-Master GB2760QSU-B1 - WQHD Gaming Monitor - 144hz - 27 inch",
    "subtitle": "144Hz en FreeSync ondersteuning!",
    "price": "324.99",
    "rating": "94%",
    "date": "2021-03-08 10:07:47.170762"
  },
  {
    "title": "Samsung Odyssey G7 LC27G75T - QLED Curved Gaming Monitor - 27 inch",
    "subtitle": "Keuze van bol.com voor fanatieke gamers die een maatje zoeken voor hun indrukwekkende gaming setup | QLED, 240hz, 1000R curve",
    "price": "569.00",
    "rating": "86%",
    "date": "2021-03-08 10:07:47.171754"
  },
  {
    "title": "AOC C27G2U - Curved Gaming Monitor - 27 inch (165hz)",
    "subtitle": "165hz gaming monitor voor de snelste shooters! Geschikt voor PC- en console gaming | FreeSync Premium | USB-Hub | In hoogte verstelbaar",
    "price": "249.00",
    "rating": "80%",
    "date": "2021-03-08 10:07:47.173242"
  }
,
  {
    "title": "AOC C27G2ZU - Curved VA Gaming Monitor - 27 inch (240hz)",
    "subtitle": "Razendsnelle 240hz gaming monitor | 0.5 ms responsetijd | 300 nits | Ingebouwde speakers | In hoogte verstelbaar | USB-HUB",
    "price": "326.80",
    "rating": "97%",
    "date": "2021-03-08 10:07:47.672365"
  },
  {
    "title": "iiyama ProLite XUB3493WQSU-B1 -  QHD IPS Monitor - 34 Inch",
    "subtitle": "Keuze van bol.com voor productiviteit met bovengemiddelde service & garantiebeleid voor professionals",
    "price": "399.00",
    "rating": "87%",
    "date": "2021-03-08 10:07:47.673964"
  },
  {
    "title": "iiyama G-MASTER GB3266QSU-B1 - QHD VA Monitor - 32 inch",
    "subtitle": null,
    "price": "369.90",
    "rating": null,
    "date": "2021-03-08 10:07:47.674860"
  },
  {
    "title": "MSI Optix G241V - Full HD IPS Gaming Monitor - 75hz - 24 inch",
    "subtitle": "De ideale (casual) gaming monitor | Smalle bezels | FreeSync en 75hz | IPS-paneel voor de beste kleurweergave en kijkhoeken",
    "price": "159.00",
    "rating": "97%",
    "date": "2021-03-08 10:07:47.676323"
  },
  {
    "title": "Acer NITRO XV2 XV240Y - IPS Gaming Monitor - 144hz - 23.8inch",
    "subtitle": null,
    "price": "189.00",
    "rating": null,
    "date": "2021-03-08 10:07:47.677318"
  },
  {
    "title": "Samsung Odyssey C32G55T - QHD Curved Gaming Monitor - 144hz - 32 inch",
    "subtitle": null,
    "price": "442.89",
    "rating": null,
    "date": "2021-03-08 10:07:47.678804"
  },
  {
    "title": "LG 24GL650 Ultragear - Full HD Gaming Monitor - 144hz - 24 inch",
    "subtitle": "Ga de strijd aan en pak de overwinning!",
    "price": "189.99",
    "rating": "100%",
    "date": "2021-03-08 10:07:47.679795"
  },
  {
    "title": "MSI Optix MAG272QP - QHD USB-C Gaming Monitor - 165hz - 27 inch",
    "subtitle": "1440p 165hz gaming monitor | Met Remote control vanaf je smartphone | Split-window | USB-C voor stroom, video en audio | FreeSync Premium",
    "price": "399.00",
    "rating": "98%",
    "date": "2021-03-08 10:07:47.681210"
  },
  {
    "title": "LG 32GK650F Ultragear - QHD VA Gaming Monitor - 144hz - 32 inch",
    "subtitle": "31,5\" QHD Gaming Monitor met FreeSync\u2122",
    "price": "341.05",
    "rating": "92%",
    "date": "2021-03-08 10:07:47.682276"
  },
  {
    "title": "iiyama G2770HSU-B1 - Full HD IPS Monitor - 165hz - 27 inch",
    "subtitle": null,
    "price": "229.00",
    "rating": null,
    "date": "2021-03-08 10:07:47.683847"
  },
  {
    "title": "iiyama G-MASTER G2740HSU - Full HD IPS Monitor - 27 inch",
    "subtitle": null,
    "price": "179.00",
    "rating": null,
    "date": "2021-03-08 10:07:47.684730"
  },
  {
    "title": "Acer Nitro RG0 60,5 cm (23.8\") 1920 x 1080 Pixels Full HD LED Zwart",
    "subtitle": null,
    "price": "149.00",
    "rating": null,
    "date": "2021-03-08 10:07:47.686243"
  },
  {
    "title": "LG 27GN800 Ultragear - QHD IPS Gaming Monitor - 144hz - 27 inch",
    "subtitle": "Inclusief 144Hz verversingssnelheid | 1 ms reactietijd | Freesync en G-sync Compatible | Geschikt voor PC- en Console gaming | Nooit meer naar de Gulag!",
    "price": "389.00",
    "rating": "94%",
    "date": "2021-03-08 10:07:47.687235"
  },
  {
    "title": "ASUS PG65UQ 163,8 cm (64.5\") 3840 x 2160 Pixels 4K Ultra HD LED Zwart",
    "subtitle": null,
    "price": "3961.95",
    "rating": null,
    "date": "2021-03-08 10:07:47.688229"
  },
  {
    "title": "BenQ Mobiuz EX2510 - IPS Gaming Monitor - 144hz -25inch",
    "subtitle": "Ontdek BenQ's nieuwe gaming lijn: Mobiuz! Premium gaming monitor met slimme oplossingen",
    "price": "239.00",
    "rating": "97%",
    "date": "2021-03-08 10:07:47.689194"
  },
  {
    "title": "MSI Optix MAG322CQR - WQHD USB-C Curved Gaming Monitor - 165hz - 32 inch",
    "subtitle": "Razendsnelle 1440p gaming monitor | Klaar voor next-gen gaming! | Ideaal voor PC- en console gamers | USB-C | In hoogte verstelbaar | Mystic light verlichting | FreeSync Premium",
    "price": "489.00",
    "rating": "91%",
    "date": "2021-03-08 10:07:47.690704"
  },
  {
    "title": "LG 32UK550 - 4K VA Gaming Monitor - 32 inch",
    "subtitle": "32\" in hoogte verstelbare 4K monitor met FreeSync ondersteuning en ingebouwde speakers!",
    "price": "374.99",
    "rating": "95%",
    "date": "2021-03-08 10:07:47.691866"
  },
  {
    "title": "Alienware AW2521HFLA - Full HD IPS Gaming Monitor - 240hz - 25 inch",
    "subtitle": null,
    "price": "379.00",
    "rating": null,
    "date": "2021-03-08 10:07:47.693190"
  },
  {
    "title": "Philips 272E1CA - Full HD Curved VA Monitor - 27 inch",
    "subtitle": null,
    "price": "179.00",
    "rating": null,
    "date": "2021-03-08 10:07:47.694674"
  },
  {
    "title": "BenQ ZOWIE XL2411P - Full HD Gaming Monitor - 144hz - 24 inch",
    "subtitle": "Gaming monitor op eSports niveau met DisplayPort een hoge verversingssnelheid van 144 Hz",
    "price": "209.00",
    "rating": "84%",
    "date": "2021-03-08 10:07:47.695669"
  },
  {
    "title": "Samsung C49HG90DMU - Curved Dual HD VA Gaming Monitor (144 Hz)",
    "subtitle": "Met QLED kleuren en HDR heeft deze monitor de beste beeldkwaliteit!",
    "price": "835.00",
    "rating": "88%",
    "date": "2021-03-08 10:07:47.696661"
  },
  {
    "title": "Philips 242E1GAEZ - Full HD Gaming Monitor - 144hz - 24 inch",
    "subtitle": null,
    "price": "189.00",
    "rating": null,
    "date": "2021-03-08 10:07:47.698146"
  },
  {
    "title": "BenQ GL2780 - Full HD TN Gaming Monitor - 27 inch",
    "subtitle": "Gaming monitor met lichtsensor en 1ms reactietijd",
    "price": "189.00",
    "rating": "89%",
    "date": "2021-03-08 10:07:47.699610"
  },
  {
    "title": "iiyama GB2770HSU-B1 - Full HD IPS Monitor - 165hz -  27 Inch",
    "subtitle": null,
    "price": "249.00",
    "rating": null,
    "date": "2021-03-08 10:07:47.700630"
  }
,
  {
    "title": "BenQ Zowie XL2546 - Full HD Gaming Monitor - 240hz - 25 inch",
    "subtitle": "De ultieme gamingmonitor op E-sports niveau met verversingssnelheid van 240 hz",
    "price": "454.00",
    "rating": "100%",
    "date": "2021-03-08 10:07:48.229609"
  },
  {
    "title": "iiyama GB3461WQSU-B1 - 34'' UWQHD Gaming IPS monitor (144Hz, 1ms)",
    "subtitle": "Ontdek de nieuwste 34'' IPS gaming monitor van iiyama voor de competitieve gamers",
    "price": "479.00",
    "rating": "87%",
    "date": "2021-03-08 10:07:48.231097"
  },
  {
    "title": "ASUS TUF VG279QM - Full HD IPS Gaming Monitor - 280hz- 27 inch",
    "subtitle": "Keuze van bol.com voor (semi)-professionele PC-gamers en de snelste shooters | Overclockbaar naar 280hz | 95% DCI-P3",
    "price": "389.00",
    "rating": "96%",
    "date": "2021-03-08 10:07:48.232088"
  },
  {
    "title": "iiyama G-MASTER GB3466WQSU-B1 - Ultrawide Gaming Monitor - 144hz - 34 inch",
    "subtitle": "Bekroond met de Hardwareinfo great value award (augustus 2020)",
    "price": "506.16",
    "rating": "87%",
    "date": "2021-03-08 10:07:48.233082"
  },
  {
    "title": "AOC 27G2AE - Full HD IPS Gaming Monitor - 27 inch",
    "subtitle": null,
    "price": "229.00",
    "rating": null,
    "date": "2021-03-08 10:07:48.234568"
  },
  {
    "title": "Alienware AW2521HFA - Full HD IPS Gaming Monitor - 25 inch - 240hz",
    "subtitle": null,
    "price": "399.00",
    "rating": null,
    "date": "2021-03-08 10:07:48.235561"
  },
  {
    "title": "Thredo TPM-01 \u2013 Full HD USB-C IPS Portable Monitor - 15.6 Inch",
    "subtitle": null,
    "price": "179.95",
    "rating": null,
    "date": "2021-03-08 10:07:48.237049"
  },
  {
    "title": "AOC Q34E2A - Ultrawide Full HD IPS Monitor - 34 inch",
    "subtitle": "Ben je het zat om te werken op een klein scherm? Ga nu voor ultrawide van AOC! Geschikt voor productiviteit & casual gaming",
    "price": "279.00",
    "rating": "89%",
    "date": "2021-03-08 10:07:48.238042"
  },
  {
    "title": "iiyama G-Master GB2730HSU-B1 - Gaming Monitor (75Hz)",
    "subtitle": "Zet het scherm in de voor jou gewenste positie door te draaien, kantelen of verhogen!",
    "price": "199.00",
    "rating": "95%",
    "date": "2021-03-08 10:07:48.239528"
  },
  {
    "title": "LG 27GL650F Ultragear - Full HD Gaming Monitor - 144hz - 27 inch",
    "subtitle": null,
    "price": "274.36",
    "rating": null,
    "date": "2021-03-08 10:07:48.240521"
  },
  {
    "title": "ASUS TUF VG259QM - Full HD  IPS Gaming Monitor - 25 inch - 240hz-280hz",
    "subtitle": "25 inch gaming monitor met 240-280hz verversingssnelheid | HDR400 | G-Sync compatible | In hoogte verstelbaar",
    "price": "379.00",
    "rating": "96%",
    "date": "2021-03-08 10:07:48.241512"
  },
  {
    "title": "MSI Optix G32CQ4 - WQHD Gaming Monitor - 165hz - 32 inch",
    "subtitle": "Curved 1440p 165hz gaming monitor | 1ms reactietijd en FreeSync Premium | Ideaal voor PC- en Console Gaming!",
    "price": "449.00",
    "rating": "94%",
    "date": "2021-03-08 10:07:48.242968"
  },
  {
    "title": "HP Elitedisplay E27 G4 - Full HD IPS Monitor - 27 inch",
    "subtitle": "Duurzame- en compacte 27'' monitor | Ergonomische keuze dankzij diverse verstelopties| HDMI-VGA-DisplayPort-USB Hub",
    "price": "249.00",
    "rating": "100%",
    "date": "2021-03-08 10:07:48.243993"
  },
  {
    "title": "ASUS VP28UQGL - 4K UHD Gaming Monitor - 28 inch (1ms)",
    "subtitle": "In hoogte verstelbaar, draaibaar en kantelbaar!",
    "price": "299.00",
    "rating": "86%",
    "date": "2021-03-08 10:07:48.245010"
  },
  {
    "title": "ASUS ROG Swift PG259QN - Full HD IPS Gaming Monitor - 24.5 inch - 360 hz",
    "subtitle": null,
    "price": "820.20",
    "rating": null,
    "date": "2021-03-08 10:07:48.246690"
  },
  {
    "title": "Iiyama ProLite XB3288UHSU-B1 - VA 4K Monitor",
    "subtitle": "Een 4K monitor die zowel gebruikt kan worden om mee te gamen evenals kantoortaken op 4K resolutie",
    "price": "419.00",
    "rating": "80%",
    "date": "2021-03-08 10:07:48.247928"
  },
  {
    "title": "iiyama GB2470HSU-B1 - Full HD IPS Monitor - 165hz - 24 inch",
    "subtitle": null,
    "price": "199.00",
    "rating": null,
    "date": "2021-03-08 10:07:48.248920"
  },
  {
    "title": "Lenovo Q27h-10 - QHD IPS USB-C Monitor - 27 inch",
    "subtitle": "Stijlvolle oplossing voor elke thuiswerkplek! | Met USB-C en 80w powerdelivery | Ingebouwde speakers | USB-hub | FreeSync | 75hz",
    "price": "403.22",
    "rating": "100%",
    "date": "2021-03-08 10:07:48.250432"
  },
  {
    "title": "iiyama GB2466HSU - Full HD VA Gaming Monitor - 165hz - 24 inch",
    "subtitle": null,
    "price": "199.00",
    "rating": null,
    "date": "2021-03-08 10:07:48.251424"
  },
  {
    "title": "Lenovo Q27Q-1L - QHD IPS Monitor - 27 Inch",
    "subtitle": "Stijlvolle oplossing voor elke thuiswerkplek! | Ingebouwde speakers | FreeSync | 75hz | 99% sRGB voor hoge kleurechtheid",
    "price": "269.00",
    "rating": "100%",
    "date": "2021-03-08 10:07:48.252417"
  },
  {
    "title": "Acer NITRO QG1 QG271bii 68,6 cm (27\") 1920 x 1080 Pixels Full HD Zwart",
    "subtitle": null,
    "price": "189.00",
    "rating": null,
    "date": "2021-03-08 10:07:48.253880"
  },
  {
    "title": "ASUS TUF VG289Q - 4K IPS Gaming Monitor - 28 inch - 60hz",
    "subtitle": null,
    "price": "392.04",
    "rating": null,
    "date": "2021-03-08 10:07:48.254897"
  },
  {
    "title": "MSI Optix G32C4 - Full HD Curved Gaming Monitor - 32 inch",
    "subtitle": "Curved Gaming Display - 165 hz en 1ms responstijd",
    "price": "299.00",
    "rating": "100%",
    "date": "2021-03-08 10:07:48.255864"
  },
  {
    "title": "Philips 499P9H - UltraWide Dual QHD Curved USB-C VA Monitor - 49 inch",
    "subtitle": "HDR400 | AdaptiveSync | USB-C dockingstation | Pop-up webcam met Windows Hello | In hoogte verstelbaar",
    "price": "1579.65",
    "rating": "90%",
    "date": "2021-03-08 10:07:48.257385"
  }
,
  {
    "title": "Dell U3419W - Ultrawide QHD USB-C IPS Monitor - 34 inch",
    "subtitle": null,
    "price": "819.00",
    "rating": null,
    "date": "2021-03-08 10:07:48.769360"
  },
  {
    "title": "LG 27UL600 - 4K IPS Monitor - 27 inch",
    "subtitle": "4K HDR monitor met Black stabilizer en speciale Game Modes",
    "price": "349.00",
    "rating": "89%",
    "date": "2021-03-08 10:07:48.770352"
  },
  {
    "title": "AOC CU34G2 - QHD Curved Gaming Monitor - 100hz - 34 Inch",
    "subtitle": null,
    "price": "429.00",
    "rating": null,
    "date": "2021-03-08 10:07:48.771344"
  },
  {
    "title": "Edutop V32FL - Ultrawide Monitor Curved - 32 inch - Pro Gaming 165 Hz",
    "subtitle": null,
    "price": "349.99",
    "rating": null,
    "date": "2021-03-08 10:07:48.772336"
  },
  {
    "title": "CHiQ 32 inch QHD (2560x1440) LED IPS-monitor - 5 ms - Randloos aan drie zijden en ultra-slank - Minder blauw licht - Geen flikkeringen",
    "subtitle": null,
    "price": "249.00",
    "rating": null,
    "date": "2021-03-08 10:07:48.773824"
  },
  {
    "title": "LG 35WN65C - QHD Curved Ultrawide Monitor - 35 inch",
    "subtitle": "Ultrawide monitor | geschikt voor video, gaming en productiviteit! | HDMI - DisplayPort - USB-Hub |",
    "price": "509.00",
    "rating": "95%",
    "date": "2021-03-08 10:07:48.774816"
  },
  {
    "title": "LG 24MK400H - Full HD TN Gaming Monitor - 24 inch",
    "subtitle": "1ms Full HD Gaming monitor met FreeSync",
    "price": "139.00",
    "rating": "89%",
    "date": "2021-03-08 10:07:48.776304"
  },
  {
    "title": "MSI Optix G271 - Full HD IPS Gaming Monitor - 144hz - 27 inch",
    "subtitle": "Vlotte 144hz gaming monitor | FreeSync - 144hz - 1 ms | IPS-paneel voor de beste kleurweergave en kijkhoeken",
    "price": "295.00",
    "rating": "97%",
    "date": "2021-03-08 10:07:48.777296"
  },
  {
    "title": "iiyama G-Master GB2560HSU-B1 - Gaming Monitor (144Hz)",
    "subtitle": "144Hz en FreeSync ondersteuning!",
    "price": "209.00",
    "rating": "94%",
    "date": "2021-03-08 10:07:48.778784"
  },
  {
    "title": "LG 35WN73A - QHD Curved Ultrawide USB-C Monitor - 100hz - 35 inch",
    "subtitle": "Met USB-C en 60w powerdelivery, geschikt voor video, gaming en productiviteit!",
    "price": "None",
    "rating": "95%",
    "date": "2021-03-08 10:07:48.779776"
  },
  {
    "title": "Acer Nitro VG270 - Gaming Monitor (75 Hz)",
    "subtitle": "Met FreeSync, 1ms reactietijd, IPS paneel en ZeroFrame design",
    "price": "199.00",
    "rating": "95%",
    "date": "2021-03-08 10:07:48.780768"
  },
  {
    "title": "LG UltraWide 34WP65G-B monitor 34",
    "subtitle": null,
    "price": "327.95",
    "rating": null,
    "date": "2021-03-08 10:07:48.781760"
  },
  {
    "title": "Philips E Line 272E1GAEZ/00 - Full HD IPS Monitor - 27 inch (144hz)",
    "subtitle": null,
    "price": "219.00",
    "rating": null,
    "date": "2021-03-08 10:07:48.782752"
  },
  {
    "title": "LG 34UM69G-B - UltraWide USB-C IPS Gaming Monitor - 34 Inch",
    "subtitle": "1ms Motion Blur Reduction",
    "price": "349.00",
    "rating": "100%",
    "date": "2021-03-08 10:07:48.784249"
  },
  {
    "title": "ASUS TUF VG259Q - Full HD IPS Gaming Monitor - 144hz - 25 inch",
    "subtitle": "Urenlang gameplezier zonder vermoeide ogen dankzij de blauwlichtfilter en trillingsvrije technologie",
    "price": "264.99",
    "rating": "95%",
    "date": "2021-03-08 10:07:48.785728"
  },
  {
    "title": "Samsung C27RG50FQU - Curved 27'' Full HD Gaming monitor",
    "subtitle": null,
    "price": "325.89",
    "rating": null,
    "date": "2021-03-08 10:07:48.786720"
  },
  {
    "title": "AOC U2879VF - 4K TN Gaming Monitor - 28 inch",
    "subtitle": "De ideale gaming monitor voor console gaming | FreeSync | HDMI - VGA - DisplayPort - DVI",
    "price": "296.80",
    "rating": "91%",
    "date": "2021-03-08 10:07:48.787712"
  },
  {
    "title": "\u00ae\ufe0fStane Polestar - IPS Portable monitor - Full HD - HDMI & USB-C - Inclusief powerbank 20.000 mah - 15.6 Inch",
    "subtitle": null,
    "price": "499.00",
    "rating": null,
    "date": "2021-03-08 10:07:48.788704"
  },
  {
    "title": "LG Ergo 27GN880 - Ultragear QHD Monitor - 144hz - 27 inch",
    "subtitle": null,
    "price": "549.00",
    "rating": null,
    "date": "2021-03-08 10:07:48.789696"
  },
  {
    "title": "MSI Optix MPG341CQR - QHD USB-C Ultrawide Gaming Monitor - 144hz - 34 inch",
    "subtitle": "Bekroond met de Hardwareinfo Excellent award (feb 2020)| Klaar voor next-gen gaming! | Ideaal voor PC- en console gamers | USB-C | In hoogte verstelbaar | Mystic light verlichting | FreeSync",
    "price": "916.72",
    "rating": "96%",
    "date": "2021-03-08 10:07:48.791184"
  },
  {
    "title": "LG 32QN600 - QHD IPS Monitor - 32 inch",
    "subtitle": null,
    "price": "349.00",
    "rating": null,
    "date": "2021-03-08 10:07:48.792176"
  },
  {
    "title": "BenQ EL2870U - 4K HDR Monitor",
    "subtitle": "Met FreeSync, 1ms, TN-paneel en automatische helderheid: de perfecte allround monitor voor ontspanning en zakelijk gebruik",
    "price": "296.84",
    "rating": "92%",
    "date": "2021-03-08 10:07:48.793168"
  },
  {
    "title": "CHiQ 27 inch FULL HD (1920x1080) LED IPS-monitor - 5 ms - Randloos aan drie zijden en ultra-slank - Minder blauw licht - Geen flikkeringen",
    "subtitle": null,
    "price": "179.00",
    "rating": null,
    "date": "2021-03-08 10:07:48.794160"
  },
  {
    "title": "Acer ED3 ED273URPBIDPX - QHD Curved Gaming monitor - 27 inch",
    "subtitle": null,
    "price": "305.00",
    "rating": null,
    "date": "2021-03-08 10:07:48.795152"
  }
,
  {
    "title": "Gigabyte M27Q 27\" QHD 170Hz monitor",
    "subtitle": null,
    "price": "399.00",
    "rating": null,
    "date": "2021-03-08 10:07:49.269489"
  },
  {
    "title": "Edutop V27FL - Ultrawide Monitor Curved - 27 inch - Pro Gaming 165 Hz",
    "subtitle": null,
    "price": "249.99",
    "rating": null,
    "date": "2021-03-08 10:07:49.270481"
  },
  {
    "title": "Samsung U28E570DS - 4K monitor",
    "subtitle": "28'' 4K monitor met TN-paneel",
    "price": "265.16",
    "rating": "100%",
    "date": "2021-03-08 10:07:49.271473"
  },
  {
    "title": "Iiyama G-Master GB2730QSU-B1 - Gaming Monitor",
    "subtitle": null,
    "price": "259.00",
    "rating": null,
    "date": "2021-03-08 10:07:49.272961"
  },
  {
    "title": "iiyama ProLite B2791QSU-B1 - WQHD Monitor",
    "subtitle": null,
    "price": "259.00",
    "rating": null,
    "date": "2021-03-08 10:07:49.273953"
  },
  {
    "title": "iiyama G-Master Black Hawk G2230HS-B1 22\" Gaming Monitor",
    "subtitle": null,
    "price": "139.00",
    "rating": null,
    "date": "2021-03-08 10:07:49.274945"
  },
  {
    "title": "Asus TUF Gaming VG279Q1A - IPS Gaming Monitor - 165hz - 27 inch",
    "subtitle": "FreeSync Premium | 165hz | Ingebouwde speakers | Dubbele HDMI-aansluiting",
    "price": "283.55",
    "rating": "100%",
    "date": "2021-03-08 10:07:49.276433"
  },
  {
    "title": "BenQ EW3270UE - 4K USB-C VA Monitor - 32 inch",
    "subtitle": "De ideale monitor voor entertainment en console gaming",
    "price": "399.00",
    "rating": "88%",
    "date": "2021-03-08 10:07:49.277425"
  },
  {
    "title": "HP 34F - QHD IPS Monitor - 34inch",
    "subtitle": null,
    "price": "582.00",
    "rating": null,
    "date": "2021-03-08 10:07:49.278913"
  },
  {
    "title": "LG 29UM69G-B - UltraWide QHD USB-C IPS Gaming Monitor - 29 Inch",
    "subtitle": "75 Hz beeldverversingssnelheid en IPS schermtechnologie",
    "price": "271.95",
    "rating": "93%",
    "date": "2021-03-08 10:07:49.279905"
  },
  {
    "title": "X27i - QHD IPS Gaming Monitor - 144hz - 27 inch",
    "subtitle": null,
    "price": "319.00",
    "rating": null,
    "date": "2021-03-08 10:07:49.280897"
  },
  {
    "title": "Lipa AX-50 portable monitor Full HD 15.6\" / HDMI / 2x USB C / Met hoes en kickstand / Ook voor Nintendo Switch, Xbox en Playstation / Makkelijk mee te nemen",
    "subtitle": "Ook voor Nintendo Switch, Xbox en Playstation| Makkelijk mee te nemen | Met hoes en kickstand met hoes",
    "price": "208.99",
    "rating": "93%",
    "date": "2021-03-08 10:07:49.281889"
  },
  {
    "title": "HP X24c - Curved Gaming Monitor - 144hz - 24 inch",
    "subtitle": null,
    "price": "189.00",
    "rating": null,
    "date": "2021-03-08 10:07:49.283377"
  },
  {
    "title": "PEPPER JOBS portable monitor XtendTouch XT1610F - draagbare monitor- Full HD USB-C IPS Touch - HDMI & USB C - ingebouwde 10.800mAh accu - 15.6 Inch",
    "subtitle": "Dit model is geschikt voor Samsung Dex, zoals bij de Samsung S21 / S20 / Note 20 modellen heeft.",
    "price": "329.95",
    "rating": "100%",
    "date": "2021-03-08 10:07:49.284369"
  },
  {
    "title": "Samsung S27F354FHU 68,6 cm (27\") 1920 x 1080 Pixels Full HD LED Zwart",
    "subtitle": null,
    "price": "170.21",
    "rating": null,
    "date": "2021-03-08 10:07:49.285361"
  },
  {
    "title": "ASUS TUF VG27VQ - Full HD Curved VA Gaming Monitor - 27 inch - 165hz",
    "subtitle": "Ervaar een haarscherpe en vloeiende gameplay met deze ultrasnelle gaming monitor",
    "price": "299.00",
    "rating": "95%",
    "date": "2021-03-08 10:07:49.286849"
  },
  {
    "title": "Alienware AW2521H - IPS Gaming Monitor - 360hz - 25 inch",
    "subtitle": null,
    "price": "665.33",
    "rating": null,
    "date": "2021-03-08 10:07:49.287841"
  },
  {
    "title": "ASUS TUF VG32VQ - QHD Curved VA Gaming Monitor - 144hz - 32 inch",
    "subtitle": null,
    "price": "498.70",
    "rating": null,
    "date": "2021-03-08 10:07:49.288833"
  },
  {
    "title": "ASUS VX279HG - Full HD IPS Gaming Monitor - 75hz",
    "subtitle": null,
    "price": "179.00",
    "rating": null,
    "date": "2021-03-08 10:07:49.289825"
  },
  {
    "title": "LG 27GL83A-B computer monitor 68,6 cm (27\") 2560 x 1440 Pixels Quad HD LED Zwart, Rood",
    "subtitle": null,
    "price": "465.26",
    "rating": null,
    "date": "2021-03-08 10:07:49.290817"
  },
  {
    "title": "BenQ XL2546K - Full HD Gaming Monitor - 240hz - 24.5 inch",
    "subtitle": null,
    "price": "509.00",
    "rating": null,
    "date": "2021-03-08 10:07:49.292305"
  },
  {
    "title": "BenQ EX3203R - UltraWide QHD Curved USB-C HDR VA Monitor - 32 Inch (144hz)",
    "subtitle": "Ultieme entertainment ervaring met deze curved 2K monitor dankzij de verversingssnelheid van 144 Hz en FreeSync 2 ondersteuning!",
    "price": "528.00",
    "rating": "89%",
    "date": "2021-03-08 10:07:49.293460"
  },
  {
    "title": "LG 27GN750 Ultragear - Full HD IPS Gaming Monitor - 240hz - 27 inch",
    "subtitle": "240 Hz in combinatie met 1 ms reactietijd, IPS paneel,  HDR 10, Free sync ondersteuning & G-sync compatible.",
    "price": "420.60",
    "rating": "100%",
    "date": "2021-03-08 10:07:49.294785"
  },
  {
    "title": "Dell S2721DGF - QHD Nano-IPS Gaming Monitor - 165hz - 27 inch",
    "subtitle": "G-sync compatible | FreeSync Premium Pro | Nano-IPS | Backlight verlichting | USB-HUB",
    "price": "499.00",
    "rating": "100%",
    "date": "2021-03-08 10:07:49.295777"
  }
,
  {
    "title": "Gigabyte M27F 27\" FHD 144Hz monitor",
    "subtitle": null,
    "price": "205.00",
    "rating": null,
    "date": "2021-03-08 10:07:49.816955"
  },
  {
    "title": "MSI Optix MAG273R - IPS Gaming Monitor - 144hz - 27inch",
    "subtitle": null,
    "price": "228.46",
    "rating": null,
    "date": "2021-03-08 10:07:49.817944"
  },
  {
    "title": "AOC Q3279VWFD8 - QHD IPS Monitor - 32 inch",
    "subtitle": "FreeSync | HDMI, VGA, DVI & DisplayPort",
    "price": "266.06",
    "rating": "85%",
    "date": "2021-03-08 10:07:49.818939"
  },
  {
    "title": "LG 32UL750 - 4K USB-C VA Monitor - 32 inch",
    "subtitle": null,
    "price": "623.00",
    "rating": null,
    "date": "2021-03-08 10:07:49.820427"
  },
  {
    "title": "Philips 243V7QDSB V Line - Full HD IPS Monitor - 23,8'' Inch",
    "subtitle": null,
    "price": "149.00",
    "rating": null,
    "date": "2021-03-08 10:07:49.821422"
  },
  {
    "title": "BenQ EX2780Q - UltraWide QHD USB-C IPS Monitor - 144hz - 27 Inch",
    "subtitle": null,
    "price": "427.13",
    "rating": null,
    "date": "2021-03-08 10:07:49.822411"
  },
  {
    "title": "BenQ EX2710 - Full HD Gaming Monitor - 144hz - 27 inch",
    "subtitle": "Ontdek BenQ's nieuwe gaming lijn: Mobiuz! Premium gaming monitor met slimme oplossingen",
    "price": "289.00",
    "rating": "97%",
    "date": "2021-03-08 10:07:49.823895"
  },
  {
    "title": "MSI Optix MAG272C - Full HD USB-C VA Gaming Monitor - 27 Inch (165hz)",
    "subtitle": null,
    "price": "309.00",
    "rating": null,
    "date": "2021-03-08 10:07:49.824905"
  },
  {
    "title": "HP OMEN 27I - IPS Gaming Monitor - 165hz - 27inch",
    "subtitle": null,
    "price": "477.00",
    "rating": null,
    "date": "2021-03-08 10:07:49.826379"
  },
  {
    "title": "iiyama G-Master Black Hawk G2530HSU-B1 24.5\" Gaming Monitor",
    "subtitle": null,
    "price": "169.95",
    "rating": null,
    "date": "2021-03-08 10:07:49.827373"
  },
  {
    "title": "Asus VG27AQL1A - QHD IPS Gaming Monitor - 144hz",
    "subtitle": "HDR400 | Overclockbaar naar 170hz |HDR400 | 95% DCI P3 | Pivot-functie | G-Sync compatible",
    "price": "549.00",
    "rating": "100%",
    "date": "2021-03-08 10:07:49.828850"
  },
  {
    "title": "Iiyama G-Master GB2760HSU-B1 - Gaming Monitor (144Hz)",
    "subtitle": null,
    "price": "249.00",
    "rating": null,
    "date": "2021-03-08 10:07:49.830002"
  },
  {
    "title": "Lipa AX-60T portable monitor 4K Ultra HD 15.6\" / Met Touchscreen / HDMI / 2x USB C & 1x Micro usb / Met hoes en kickstand / Ook voor Nintendo Switch, Xbox en Playstation / Makkelijk mee te nemen",
    "subtitle": null,
    "price": "369.99",
    "rating": null,
    "date": "2021-03-08 10:07:49.830849"
  },
  {
    "title": "Acer KG1 KG271UA 68,6 cm (27\") 2560 x 1440 Pixels Quad HD Zwart",
    "subtitle": null,
    "price": "310.34",
    "rating": null,
    "date": "2021-03-08 10:07:49.832334"
  },
  {
    "title": "Acer Nitro VG270U - WQHD Gaming Monitor (75Hz)",
    "subtitle": "Met FreeSync, 1ms reactietijd, WQHD schem, IPS paneel en ZeroFrame design",
    "price": "281.80",
    "rating": "95%",
    "date": "2021-03-08 10:07:49.833323"
  },
  {
    "title": "PEPPER JOBS portable monitor XtendViz XV1610F - draagbare monitor- Full HD USB-C IPS - HDMI & USB C - Samsung Dex - 15.6 Inch",
    "subtitle": "LET OP: heeft geen ingebouwde accu, maar gebruik je via een USB-C aansluiting. Met 1-kabel heb je dus beeldoverdracht- en stroomoverdracht!",
    "price": "219.95",
    "rating": null,
    "date": "2021-03-08 10:07:49.834315"
  },
  {
    "title": "Alienware AW2521HFL 62,2 cm (24.5\") 1920 x 1080 Pixels Full HD LCD Zwart",
    "subtitle": null,
    "price": "435.39",
    "rating": null,
    "date": "2021-03-08 10:07:49.835770"
  },
  {
    "title": "Gigabyte AORUS CV27Q computer monitor",
    "subtitle": null,
    "price": "439.95",
    "rating": null,
    "date": "2021-03-08 10:07:49.836763"
  },
  {
    "title": "Dell S3220DGF - QHD VA Gaming Monitor - 165Hz - 32 inch",
    "subtitle": null,
    "price": "485.00",
    "rating": null,
    "date": "2021-03-08 10:07:49.838283"
  },
  {
    "title": "Acer VG240YP 60,5 cm (23.8\") 1920 x 1080 Pixels Full HD LED Zwart",
    "subtitle": null,
    "price": "199.00",
    "rating": null,
    "date": "2021-03-08 10:07:49.839242"
  },
  {
    "title": "Gigabyte G27Q 68,6 cm (27\") 2560 x 1440 Pixels Quad HD LED Zwart",
    "subtitle": null,
    "price": "418.79",
    "rating": null,
    "date": "2021-03-08 10:07:49.840763"
  },
  {
    "title": "BenQ ZOWIE XL2740 - Full HD Gaming Monitor - 240hz- 27 inch",
    "subtitle": null,
    "price": "529.00",
    "rating": null,
    "date": "2021-03-08 10:07:49.841755"
  },
  {
    "title": "Mini monitor 3.5 inch H 1024 Capacitive Touch Screen LCD met case Support",
    "subtitle": null,
    "price": "69.99",
    "rating": null,
    "date": "2021-03-08 10:07:49.843211"
  },
  {
    "title": "HP 27wm 68,6 cm (27\") 1920 x 1080 Pixels Full HD LCD Zwart",
    "subtitle": null,
    "price": "172.50",
    "rating": null,
    "date": "2021-03-08 10:07:49.844238"
  }
,
  {
    "title": "BenQ XL2411K - E-Sports Gaming Monitor - 144hz - 24 inch",
    "subtitle": null,
    "price": "239.00",
    "rating": null,
    "date": "2021-03-08 10:07:50.375397"
  },
  {
    "title": "BenQ EX3501R - QHD Curved USB-C VA Gaming Monitor - 35 inch",
    "subtitle": "HDR monitor met FreeSync, 100Hz en 4 ms, in hoogte verstelbare voet en USB type C aansluiting!",
    "price": "699.00",
    "rating": "89%",
    "date": "2021-03-08 10:07:50.376885"
  },
  {
    "title": "Dell S2721HGF  - Full HD VA Monitor - 144hz - 27 inch",
    "subtitle": null,
    "price": "239.00",
    "rating": null,
    "date": "2021-03-08 10:07:50.377877"
  },
  {
    "title": "ASUS VG249Q1R - IPS Gaming Monitor - 144-165hz - 24 inch",
    "subtitle": "FreeSync Premium | Overclockbaar naar 165hz | Ingebouwde speakers | Dubbele HDMI-aansluiting",
    "price": "238.81",
    "rating": "80%",
    "date": "2021-03-08 10:07:50.378869"
  },
  {
    "title": "Acer Nitro VG271UP - WQHD Gaming Monitor (144hz)",
    "subtitle": "Met FreeSync, 1 MS reactietijd, IPS paneel, HDR400 en ZeroFrame Design",
    "price": "475.79",
    "rating": "74%",
    "date": "2021-03-08 10:07:50.380357"
  },
  {
    "title": "ASUS ROG Swift PG329Q - QHD IPS Monitor - 32 Inch",
    "subtitle": null,
    "price": "852.93",
    "rating": null,
    "date": "2021-03-08 10:07:50.381349"
  },
  {
    "title": "Samsung C32HG70 - Gaming HDR Monitor",
    "subtitle": "Met QLED kleuren en HDR heeft deze monitor de beste beeldkwaliteit!",
    "price": "542.60",
    "rating": "85%",
    "date": "2021-03-08 10:07:50.382341"
  },
  {
    "title": "MSI Optix MAG274R - Full HD USB-C IPS Gaming Monitor \u2013 27 inch (144hz)",
    "subtitle": null,
    "price": "347.27",
    "rating": null,
    "date": "2021-03-08 10:07:50.383829"
  },
  {
    "title": "Gigabyte G27QC - LED-Monitor - Gebogen (1500R) - 27\" VA - 2560 x 1440 QHD - 165 Hz - 1 ms - 250 cd/m\u00b2 - 3000:1",
    "subtitle": null,
    "price": "375.00",
    "rating": null,
    "date": "2021-03-08 10:07:50.385317"
  },
  {
    "title": "Asus VG27AQ1A - QHD IPS Gaming Monitor - 170hz - 27 inch",
    "subtitle": null,
    "price": "469.50",
    "rating": null,
    "date": "2021-03-08 10:07:50.386805"
  },
  {
    "title": "ERAZER X53275 Gaming Monitor | 80 cm (31.5 Inch') | 2560 x 1440 Pixels | Wide Quad HD | LCD | Zwart",
    "subtitle": null,
    "price": "299.00",
    "rating": null,
    "date": "2021-03-08 10:07:50.388293"
  },
  {
    "title": "LG 32GK850G Ultragear - QHD G-Sync Gaming Monitor - 165hz - 32 inch",
    "subtitle": "Hardware.info Excellent Award december 2017",
    "price": "646.90",
    "rating": "100%",
    "date": "2021-03-08 10:07:50.389781"
  },
  {
    "title": "Dell Alienware AW2518H - G-Sync Gaming Monitor (240Hz)",
    "subtitle": null,
    "price": "None",
    "rating": null,
    "date": "2021-03-08 10:07:50.390773"
  },
  {
    "title": "Acer Nitro RG0 68,6 cm (27\") 1920 x 1080 Pixels Full HD LED Zwart",
    "subtitle": null,
    "price": "205.00",
    "rating": null,
    "date": "2021-03-08 10:07:50.392261"
  },
  {
    "title": "AOC C24G2AE - Full HD Curved VA Gaming Monitor - 24 inch (165hz)",
    "subtitle": "165hz gaming monitor voor de snelste shooters! Geschikt voor PC- en console gaming | FreeSync Premium | In hoogte verstelbaar",
    "price": "240.56",
    "rating": "93%",
    "date": "2021-03-08 10:07:50.393253"
  },
  {
    "title": "Hori  Draagbare Gaming Monitor - Geschikt voor consoles",
    "subtitle": null,
    "price": "249.99",
    "rating": null,
    "date": "2021-03-08 10:07:50.394741"
  },
  {
    "title": "LG 24TL510V-PZ LED display 59,9 cm (23.6\") 1366 x 768 Pixels HD Zwart",
    "subtitle": null,
    "price": "175.00",
    "rating": null,
    "date": "2021-03-08 10:07:50.396229"
  },
  {
    "title": "PEPPER JOBS portable monitor XtendTouch XT1310F - draagbare monitor- Full HD USB-C IPS Touch - HDMI & USB C  - Samsung Dex - 13.3 Inch",
    "subtitle": "LET OP: heeft geen ingebouwde accu, maar gebruik je via een USB-C aansluiting. Met 1-kabel heb je dus beeldoverdracht- en stroomoverdracht!",
    "price": "259.95",
    "rating": "80%",
    "date": "2021-03-08 10:07:50.397221"
  },
  {
    "title": "ASUS TUF VG27BQ - QHD Gaming Monitor - 165hz - 27 inch",
    "subtitle": "165hz gaming monitor | G-Sync compatible | 1 ms g2g reactietijd | In hoogte verstelbaar, draaibaar en kantelbaar",
    "price": "439.00",
    "rating": "97%",
    "date": "2021-03-08 10:07:50.398709"
  },
  {
    "title": "Lipa AX-60 portable monitor 4K Ultra HD 15.6\" / HDMI / 2x USB C & 1x Micro usb / Met hoes en kickstand / Ook voor Nintendo Switch, Xbox en Playstation / Makkelijk mee te nemen",
    "subtitle": null,
    "price": "309.99",
    "rating": null,
    "date": "2021-03-08 10:07:50.399701"
  },
  {
    "title": "Iiyama ProLite B2875UHSU-B1 - 4K Monitor",
    "subtitle": null,
    "price": "369.00",
    "rating": null,
    "date": "2021-03-08 10:07:50.400693"
  },
  {
    "title": "Samsung C27RG54FQU 68,6 cm (27\") 1920 x 1080 Pixels Full HD LED Blauw, Grijs",
    "subtitle": null,
    "price": "359.79",
    "rating": null,
    "date": "2021-03-08 10:07:50.402181"
  },
  {
    "title": "LG 29UM59-P computer monitor 73,7 cm (29\") 2560 x 1080 Pixels QXGA LED Zwart",
    "subtitle": "Uitstekende allround Ultrawide IPS Monitor",
    "price": "299.95",
    "rating": "95%",
    "date": "2021-03-08 10:07:50.403172"
  },
  {
    "title": "Asus TUF Gaming VG328H1B - Curved Monitor - 32 inch - 165hz",
    "subtitle": "Een Full HD monitor met specificaties die zorgen voor een extreem vloeiende gameplay zonder stotterend beeld",
    "price": "380.39",
    "rating": "100%",
    "date": "2021-03-08 10:07:50.404165"
  }
,
  {
    "title": "LC-Power LC-M34-UWQHD-144-C computer monitor 86,4 cm (34\") 3440 x 1440 Pixels UltraWide Quad HD Zwart, Rood",
    "subtitle": null,
    "price": "505.38",
    "rating": null,
    "date": "2021-03-08 10:07:50.896292"
  },
  {
    "title": "Acer Nitro VG240YU - Gaming Monitor (75Hz)",
    "subtitle": "Met FreeSync, 1ms reactietijd, WQHD schem, IPS paneel en ZeroFrame design",
    "price": "246.16",
    "rating": "95%",
    "date": "2021-03-08 10:07:50.897284"
  },
  {
    "title": "AOC AG273QZ - QHD TN Gaming Monitor - 240hz - 27 inch",
    "subtitle": null,
    "price": "658.46",
    "rating": null,
    "date": "2021-03-08 10:07:50.898276"
  },
  {
    "title": "ASUS VG248QZ - Full HD Gaming Monitor - 24 inch (1ms, 144 Hz)",
    "subtitle": "Met ingebouwde speakers en HDMI, Dual-link DVI-D en DisplayPort ingangen!",
    "price": "202.10",
    "rating": "60%",
    "date": "2021-03-08 10:07:50.899268"
  },
  {
    "title": "MSI Optix MAG341CQ - UWQHD Curved Gaming Monitor",
    "subtitle": null,
    "price": "None",
    "rating": null,
    "date": "2021-03-08 10:07:50.900260"
  },
  {
    "title": "AOC 24G2U5 - Full HD Gaming Monitor - 75hz - 24 inch",
    "subtitle": "De ideale 24 inch gaming monitor voor (casual) gaming en dagelijks gebruik!",
    "price": "196.21",
    "rating": "96%",
    "date": "2021-03-08 10:07:50.901252"
  },
  {
    "title": "LG 34GK950G-B 1- Curved G-Sync Gaming Monitor (100 Hz, 120 Hz overclock)",
    "subtitle": "34\" UltraWide\u2122 QHD Curved Gaming Monitor met G-Sync\u2122",
    "price": "990.42",
    "rating": "100%",
    "date": "2021-03-08 10:07:50.903236"
  },
  {
    "title": "Antgamer M34G5Q - QHD Ultrawide Gaming Monitor (100 Hz)",
    "subtitle": null,
    "price": "509.99",
    "rating": null,
    "date": "2021-03-08 10:07:50.904228"
  },
  {
    "title": "LC-Power LC-M24-FHD-144-C-V2 computer monitor 59,9 cm (23.6\") 1920 x 1080 Pixels Full HD Zwart",
    "subtitle": null,
    "price": "208.04",
    "rating": null,
    "date": "2021-03-08 10:07:50.905220"
  },
  {
    "title": "BenQ ZOWIE RL2460S - 24'' E-Sports Console Gaming Monitor",
    "subtitle": "In hoogte verstelbare gaming monitor voor consoles en pc op E-Sports niveau met ingebouwde speakers!",
    "price": "218.35",
    "rating": "100%",
    "date": "2021-03-08 10:07:50.906212"
  },
  {
    "title": "Samsung C27HG70 - QLED Gaming Monitor",
    "subtitle": "Met QLED kleuren en HDR heeft deze monitor de beste beeldkwaliteit!",
    "price": "498.66",
    "rating": "85%",
    "date": "2021-03-08 10:07:50.907700"
  },
  {
    "title": "Asus VG279QL1A - Full HD IPS Gaming Monitor - 27 Inch (165hz)",
    "subtitle": null,
    "price": "329.00",
    "rating": null,
    "date": "2021-03-08 10:07:50.908692"
  },
  {
    "title": "HP OMEN X 25F - TN Gaming Monitor - 240hz - 25inch",
    "subtitle": "Freesync | G-Sync compatible | USB Hub | Hoogte verstelbaar | Sfeerverlichting | Geschikt voor E-sports",
    "price": "365.00",
    "rating": "100%",
    "date": "2021-03-08 10:07:50.909684"
  },
  {
    "title": "Acer Predator X34P - Curved Gaming Monitor",
    "subtitle": null,
    "price": "949.98",
    "rating": null,
    "date": "2021-03-08 10:07:50.911172"
  },
  {
    "title": "AOC AGON AG241QG - WQHD Gaming Monitor (165 Hz)",
    "subtitle": "Met G-Sync ondersteuning en een 1ms reactietijd",
    "price": "494.24",
    "rating": "88%",
    "date": "2021-03-08 10:07:50.912164"
  },
  {
    "title": "CHiQ 24 inch FULL HD LED IPS-monitor - 5 ms - Randloos aan drie zijden en ultra-slank - Minder blauw licht - Geen flikkeringen",
    "subtitle": null,
    "price": "159.00",
    "rating": null,
    "date": "2021-03-08 10:07:50.913156"
  },
  {
    "title": "LG 27QN600 - QHD IPS Monitor - 27 inch",
    "subtitle": null,
    "price": "319.00",
    "rating": null,
    "date": "2021-03-08 10:07:50.914644"
  },
  {
    "title": "LC-Power LC-M34-UWQHD-100-C computer monitor 86,4 cm (34\") 3440 x 1440 Pixels UltraWide Quad HD Zwart, Zilver, Wit",
    "subtitle": null,
    "price": "447.67",
    "rating": null,
    "date": "2021-03-08 10:07:50.915636"
  },
  {
    "title": "Antgamer M32G5Q computer monitor 80 cm (31.5\") 2560 x 1440 Pixels Quad HD LCD Zwart",
    "subtitle": null,
    "price": "399.99",
    "rating": null,
    "date": "2021-03-08 10:07:50.916666"
  },
  {
    "title": "HKC M27G2 68,6 cm (27 inch) Curved frameless Gaming Monitor (FHD 1920x1080 Pixel, 1ms responstijd, HDMI, VGA, DisplayPort, 144 Hz, Free-Sync) zwart",
    "subtitle": null,
    "price": "299.99",
    "rating": null,
    "date": "2021-03-08 10:07:50.918116"
  },
  {
    "title": "ProXtend PX-D3434141 computer monitor 86,4 cm (34\") 3440 x 1440 Pixels UltraWide Quad HD LED Zwart",
    "subtitle": null,
    "price": "799.99",
    "rating": null,
    "date": "2021-03-08 10:07:50.919108"
  },
  {
    "title": "Samsung C27FG70 - Curved Gaming Monitor",
    "subtitle": null,
    "price": "349.47",
    "rating": null,
    "date": "2021-03-08 10:07:50.920264"
  },
  {
    "title": "AOC AGON AG273QCG - WQHD Gaming Monitor (144 Hz)",
    "subtitle": "G-Sync | In hoogte verstelbaar | USB-hub | Ingebouwde speakers",
    "price": "649.00",
    "rating": "100%",
    "date": "2021-03-08 10:07:50.921588"
  },
  {
    "title": "AOC AG353UCG - 35\" WQHD Gaming Monitor met Gsync (200 Hz)",
    "subtitle": null,
    "price": "1668.95",
    "rating": null,
    "date": "2021-03-08 10:07:50.922580"
  }
,
  {
    "title": "Lenovo G34w-10 86,4 cm (34\") 3440 x 1440 Pixels UltraWide Quad HD Zwart",
    "subtitle": null,
    "price": "559.38",
    "rating": null,
    "date": "2021-03-08 10:07:51.469276"
  },
  {
    "title": "ASUS XG49VQ - Curved UltraWide VA Gaming Monitor - 49 inch (144Hz)",
    "subtitle": "Curved, groot, razendsnel en met ingebouwde speakers + een in hoogte verstelbare voet.",
    "price": "974.00",
    "rating": null,
    "date": "2021-03-08 10:07:51.470268"
  },
  {
    "title": "Gigabyte G27FC 68,6 cm (27\") 1920 x 1080 Pixels Full HD LED Zwart",
    "subtitle": null,
    "price": "293.95",
    "rating": null,
    "date": "2021-03-08 10:07:51.471260"
  },
  {
    "title": "Viewsonic XG240R computer monitor 61 cm (24\") 1920 x 1080 Pixels Full HD LED Zwart",
    "subtitle": null,
    "price": "None",
    "rating": null,
    "date": "2021-03-08 10:07:51.472252"
  },
  {
    "title": "HP OMEN X by HP 35 - Curved Monitor",
    "subtitle": "Beleef gamen zoals het is bedoeld",
    "price": "1169.00",
    "rating": null,
    "date": "2021-03-08 10:07:51.473243"
  },
  {
    "title": "TELEPAD Portable Monitor 13.3-inch TouchScreen",
    "subtitle": null,
    "price": "389.00",
    "rating": null,
    "date": "2021-03-08 10:07:51.474236"
  },
  {
    "title": "AOC 16T2 - Portable Touch Screen Monitor - USB-C - 15 inch",
    "subtitle": "Portable monitor met ingebouwde accu | Geschikt voor gaming | 2x-USB-C & Micro HDMI | Touchscreen |  Gecertificeerd voor Windows 10 Touch Support  | Ingebouwde speakers",
    "price": "299.00",
    "rating": null,
    "date": "2021-03-08 10:07:51.475228"
  },
  {
    "title": "ASUS VZ239HE - Full HD IPS Monitor - 23\" Inch",
    "subtitle": null,
    "price": "159.99",
    "rating": null,
    "date": "2021-03-08 10:07:51.476716"
  },
  {
    "title": "Lenovo L24e-20 - Full HD Monitor",
    "subtitle": null,
    "price": "None",
    "rating": null,
    "date": "2021-03-08 10:07:51.477707"
  },
  {
    "title": "MSI Creator PS321QR - QHD IPS USB-C Monitor - 165hz - 32 inch",
    "subtitle": null,
    "price": "899.00",
    "rating": null,
    "date": "2021-03-08 10:07:51.478700"
  },
  {
    "title": "AOC AG273QXP - 2K IPS Gaming Monitor - 165hz - 27 inch",
    "subtitle": null,
    "price": "479.00",
    "rating": null,
    "date": "2021-03-08 10:07:51.479692"
  },
  {
    "title": "LG 22MK430H-B - Gaming Monitor",
    "subtitle": "Full-HD IPS scherm met 5ms responsietijd, 75 Hz verversingssnelheid FreeSync\u2122",
    "price": "127.50",
    "rating": null,
    "date": "2021-03-08 10:07:51.480684"
  },
  {
    "title": "ASUS VA24DQLB - Full HD Monitor - 24 inch",
    "subtitle": null,
    "price": "195.00",
    "rating": null,
    "date": "2021-03-08 10:07:51.481676"
  },
  {
    "title": "AOC Gaming 27G2U5/BK computer monitor 68,6 cm (27\") 1920 x 1080 Pixels Full HD LED Zwart",
    "subtitle": null,
    "price": "234.96",
    "rating": null,
    "date": "2021-03-08 10:07:51.482668"
  },
  {
    "title": "ASUS VG279Q - IPS Gaming Monitor - 27 inch (1ms, 144Hz)",
    "subtitle": "Urenlang gamen zonder vermoeide ogen dankzij de Flicker-Free en Ultra Low Blue Light technologie",
    "price": "307.90",
    "rating": "89%",
    "date": "2021-03-08 10:07:51.484156"
  },
  {
    "title": "Z32 - 4K USB-C IPS monitor - 31.5 Inch",
    "subtitle": null,
    "price": "725.90",
    "rating": null,
    "date": "2021-03-08 10:07:51.485148"
  },
  {
    "title": "Asus VG275Q - Gaming Monitor",
    "subtitle": null,
    "price": "227.00",
    "rating": null,
    "date": "2021-03-08 10:07:51.486140"
  },
  {
    "title": "Acer Predator UM.HX0EE.S01 computer monitor 68,6 cm (27\") 2560 x 1440 Pixels Quad HD IPS Zwart",
    "subtitle": null,
    "price": "523.60",
    "rating": null,
    "date": "2021-03-08 10:07:51.487131"
  },
  {
    "title": "Clever PM - Portable Monitor - 15,6 Inch - Full HD - 1920x1080",
    "subtitle": null,
    "price": "219.99",
    "rating": null,
    "date": "2021-03-08 10:07:51.488124"
  },
  {
    "title": "ASUS ROG Strix XG17AHP - Full HD USB-C IPS Monitor - 17.3 Inch",
    "subtitle": null,
    "price": "619.00",
    "rating": null,
    "date": "2021-03-08 10:07:51.489612"
  },
  {
    "title": "Hannspree Hanns.G HS 275 HFB 68,6 cm (27\") 1920 x 1080 Pixels Full HD LED Zwart, Grijs",
    "subtitle": null,
    "price": "174.65",
    "rating": null,
    "date": "2021-03-08 10:07:51.490604"
  },
  {
    "title": "DELL S2419HGF - Full HD G-Sync Compatible Gaming Monitor - 144hz",
    "subtitle": null,
    "price": "334.99",
    "rating": null,
    "date": "2021-03-08 10:07:51.491596"
  },
  {
    "title": "Gigabyte AORUS FI27Q 68,6 cm (27\") 2560 x 1440 Pixels 2K Ultra HD LED Zwart",
    "subtitle": null,
    "price": "535.00",
    "rating": null,
    "date": "2021-03-08 10:07:51.492588"
  },
  {
    "title": "Samsung C27H580F - Full HD Monitor",
    "subtitle": "Game zonder vertraging door FreeSync!",
    "price": "349.95",
    "rating": "100%",
    "date": "2021-03-08 10:07:51.494076"
  }
,
  {
    "title": "Denver MLC-2702G 68,6 cm (27\") 1920 x 1080 Pixels Full HD LED Wit",
    "subtitle": null,
    "price": "259.00",
    "rating": null,
    "date": "2021-03-08 10:07:52.157134"
  },
  {
    "title": "Mobiele monitor - Draagbare monitor - Draagbaar scherm - 2 schermen - 1080p Full HD - Alles meegeleverd - Tabletscherm - Ultra slim - Ingebouwde speakers",
    "subtitle": null,
    "price": "320.00",
    "rating": null,
    "date": "2021-03-08 10:07:52.158126"
  },
  {
    "title": "Fujitsu Displays B27-9 TS QHD 68,6 cm (27\") 2560 x 1440 Pixels Quad HD IPS Zwart",
    "subtitle": null,
    "price": "322.86",
    "rating": null,
    "date": "2021-03-08 10:07:52.159118"
  },
  {
    "title": "EIZO FlexScan EV2456-WT LED display 61,2 cm (24.1\") 1920 x 1200 Pixels WUXGA Wit",
    "subtitle": null,
    "price": "451.63",
    "rating": null,
    "date": "2021-03-08 10:07:52.160606"
  },
  {
    "title": "LG 24GL600F - Gaming Monitor (144 Hz)",
    "subtitle": "Gaming monitor met supersnelle responsietijd en verversing",
    "price": "207.95",
    "rating": "100%",
    "date": "2021-03-08 10:07:52.161598"
  },
  {
    "title": "Alienware AW3420DW computer monitor 86,6 cm (34.1\") 3440 x 1440 Pixels Quad HD LCD Zwart, Wit",
    "subtitle": null,
    "price": "1164.99",
    "rating": null,
    "date": "2021-03-08 10:07:52.162590"
  },
  {
    "title": "LC-Power LC-M32-QHD-144-C-V2 computer monitor 80 cm (31.5\") 2560 x 1440 Pixels Quad HD Zwart",
    "subtitle": null,
    "price": "375.90",
    "rating": null,
    "date": "2021-03-08 10:07:52.163582"
  },
  {
    "title": "Asus VP278QG - Gaming Monitor",
    "subtitle": null,
    "price": "195.00",
    "rating": null,
    "date": "2021-03-08 10:07:52.165070"
  },
  {
    "title": "HP Omen X Emperium 65 (4JF30AA)",
    "subtitle": null,
    "price": "2399.00",
    "rating": null,
    "date": "2021-03-08 10:07:52.166062"
  },
  {
    "title": "MEDION AKOYA X53411 - UWQHD Ultrawide Monitor - 100hz - 34 inch",
    "subtitle": null,
    "price": "539.00",
    "rating": null,
    "date": "2021-03-08 10:07:52.167054"
  },
  {
    "title": "AOC G2590PX - Full HD TN Gaming Monitor - 144hz - 25 inch",
    "subtitle": "Met FreeSync ondersteuning en een reactietijd van 1ms - in hoogte verstelbaar",
    "price": "245.00",
    "rating": "95%",
    "date": "2021-03-08 10:07:52.168046"
  },
  {
    "title": "Mon V24 F-HD / 24inch / HDMI / VGA",
    "subtitle": null,
    "price": "139.40",
    "rating": null,
    "date": "2021-03-08 10:07:52.169534"
  },
  {
    "title": "AOC G2790PX - Full HD Gaming Monitor",
    "subtitle": "Met FreeSync ondersteuning en een reactietijd van 1ms - in hoogte verstelbaar",
    "price": "321.93",
    "rating": "100%",
    "date": "2021-03-08 10:07:52.170526"
  },
  {
    "title": "Acer Predator XB271HUbmiprz - WQHD G-Sync Gaming Monitor",
    "subtitle": "Snelle gaming monitor met 100% sRGB IPS scherm en G-Sync",
    "price": "647.02",
    "rating": "100%",
    "date": "2021-03-08 10:07:52.171518"
  },
  {
    "title": "Samsung U28E590D Monitor 28Inch/ 4K / DP / 2x HDMI / Zilver",
    "subtitle": null,
    "price": "None",
    "rating": null,
    "date": "2021-03-08 10:07:52.172510"
  },
  {
    "title": "LG 34UC79G - Ultrawide Gaming Monitor",
    "subtitle": "34 inch breed, curved en 144 hz beeldverversing: nooit meer haperend beeld",
    "price": "None",
    "rating": "90%",
    "date": "2021-03-08 10:07:52.173502"
  },
  {
    "title": "Lenovo C32q-20 31.5 inch IPS monitor met AMD FreeSync (2560x1440 Quad-HD, DisplayPort 1.2, HDMI 1.4)",
    "subtitle": null,
    "price": "288.95",
    "rating": null,
    "date": "2021-03-08 10:07:52.174990"
  },
  {
    "title": "Viewsonic VX Series VX3276-4K-mhd 81,3 cm (32\") 3840 x 2160 Pixels 4K Ultra HD LED Zilver",
    "subtitle": null,
    "price": "447.20",
    "rating": null,
    "date": "2021-03-08 10:07:52.175982"
  },
  {
    "title": "Acer XF272UP - WQHD TN Gaming Monitor (144 Hz)",
    "subtitle": "met FreeSync, 1 ms reactietijd, TN-paneel en in hoogte verstelbaar",
    "price": "None",
    "rating": "73%",
    "date": "2021-03-08 10:07:52.176974"
  },
  {
    "title": "ASUS PG248Q - Full HD TN Gaming monitor (180 Hz)",
    "subtitle": "Gaming monitor met G-sync ondersteuning en verversingssnelheid van 180 Hz!",
    "price": "462.87",
    "rating": "90%",
    "date": "2021-03-08 10:07:52.177966"
  },
  {
    "title": "Viewsonic VX Series VX2758-2KP-MHD LED display 68,6 cm (27\") 2560 x 1440 Pixels Quad HD Zwart",
    "subtitle": null,
    "price": "339.00",
    "rating": null,
    "date": "2021-03-08 10:07:52.178958"
  },
  {
    "title": "Dell S2421HGF - Gaming Monitor - 144hz - 24 inch",
    "subtitle": null,
    "price": "236.63",
    "rating": null,
    "date": "2021-03-08 10:07:52.180446"
  },
  {
    "title": "Samsung U28E850R - 4K Monitor",
    "subtitle": null,
    "price": "None",
    "rating": null,
    "date": "2021-03-08 10:07:52.181438"
  },
  {
    "title": "Benq XL2746S - Full HD Gaming Monitor Monitor - 240hz- 27 Inch",
    "subtitle": null,
    "price": "629.00",
    "rating": null,
    "date": "2021-03-08 10:07:52.182430"
  }
,
  {
    "title": "Acer Predator Z321QU 80 cm (31.5\") 2560 x 1440 Pixels Wide Quad HD LED Zwart",
    "subtitle": null,
    "price": "None",
    "rating": null,
    "date": "2021-03-08 10:07:52.629791"
  },
  {
    "title": "ASUS VG278QF - Full HD Gaming Monitor - 27 inch (0.5ms, 165Hz)",
    "subtitle": null,
    "price": "282.94",
    "rating": null,
    "date": "2021-03-08 10:07:52.630783"
  },
  {
    "title": "Lenovo Legion Y25-25 62,2 cm (24.5\") 1920 x 1080 Pixels Full HD LED Zwart",
    "subtitle": null,
    "price": "369.28",
    "rating": null,
    "date": "2021-03-08 10:07:52.631775"
  },
  {
    "title": "LC-Power LC-M32-QHD-144-C computer monitor 80 cm (31.5\") 2560 x 1440 Pixels Quad HD Zwart",
    "subtitle": null,
    "price": "None",
    "rating": null,
    "date": "2021-03-08 10:07:52.632767"
  },
  {
    "title": "Samsung LC27FG73FQU - Curved Gaming Monitor (144 Hz)",
    "subtitle": "Met 144Hz verversingssnelheid en 1ms reactietijd is deze monitor erg geschikt voor de gamer! ",
    "price": "588.34",
    "rating": "95%",
    "date": "2021-03-08 10:07:52.633759"
  },
  {
    "title": "ProXtend PX-D2725141 computer monitor 68,6 cm (27\") 2560 x 1440 Pixels UltraWide Quad HD LED Zwart",
    "subtitle": null,
    "price": "549.99",
    "rating": null,
    "date": "2021-03-08 10:07:52.634751"
  },
  {
    "title": "AOC AGON AG251FZ - Gaming Monitor (240 Hz)",
    "subtitle": "De ideale gaming monitor dankzij 240 Hz verversingssnelheid, 1 ms reactietijd en AdaptiveSync ondersteuning",
    "price": "396.78",
    "rating": "100%",
    "date": "2021-03-08 10:07:52.636239"
  },
  {
    "title": "BenQ ZOWIE XL2430 - Gaming Monitor",
    "subtitle": "Offici\u00eble toernooi-monitor van de DreamHack Open 2016/2017 en meerdere eSports toernooien!",
    "price": "None",
    "rating": "93%",
    "date": "2021-03-08 10:07:52.637231"
  },
  {
    "title": "Wortmann AG TERRA LED 2462W 60,5 cm (23.8\") 1920 x 1080 Pixels Full HD Zwart, Zilver",
    "subtitle": null,
    "price": "175.70",
    "rating": null,
    "date": "2021-03-08 10:07:52.638223"
  },
  {
    "title": "Iiyama G-Master GE2288HS-B1 - Gaming Monitor",
    "subtitle": null,
    "price": "None",
    "rating": null,
    "date": "2021-03-08 10:07:52.639215"
  },
  {
    "title": "LG 32GK850F-B computer monitor 80 cm (31.5\") 2560 x 1440 Pixels Quad HD LED Zwart",
    "subtitle": null,
    "price": "582.89",
    "rating": null,
    "date": "2021-03-08 10:07:52.640207"
  },
  {
    "title": "Acer XB271HUAbmiprz - Monitor",
    "subtitle": null,
    "price": "545.89",
    "rating": null,
    "date": "2021-03-08 10:07:52.641199"
  },
  {
    "title": "LC-Power LC-M34-UWQHD-100-C-V2 computer monitor 86,4 cm (34\") 3440 x 1440 Pixels UltraWide Quad HD Zilver, Wit",
    "subtitle": null,
    "price": "444.21",
    "rating": null,
    "date": "2021-03-08 10:07:52.642191"
  },
  {
    "title": "ASUS TUF Gaming VG259QR  - Full HD IPS Gaming Monitor - 24.5 inch - 165 hz",
    "subtitle": null,
    "price": "279.00",
    "rating": null,
    "date": "2021-03-08 10:07:52.643183"
  },
  {
    "title": "Viewsonic Elite XG270QG LED display 68,6 cm (27\") 2560 x 1440 Pixels Quad HD Zwart",
    "subtitle": null,
    "price": "799.00",
    "rating": null,
    "date": "2021-03-08 10:07:52.644175"
  },
  {
    "title": "ProXtend PX-D2425141 computer monitor 60,5 cm (23.8\") 2560 x 1440 Pixels UltraWide Quad HD LED Zwart",
    "subtitle": null,
    "price": "439.99",
    "rating": null,
    "date": "2021-03-08 10:07:52.645167"
  },
  {
    "title": "ASUS VP279QGL 68,6 cm (27\") 1920 x 1080 Pixels Full HD LED Zwart",
    "subtitle": null,
    "price": "275.00",
    "rating": null,
    "date": "2021-03-08 10:07:52.646655"
  },
  {
    "title": "Acer B7 B277Ubmiipprzx 68,6 cm (27\") 2560 x 1440 Pixels Quad HD LED Zwart",
    "subtitle": null,
    "price": "329.00",
    "rating": null,
    "date": "2021-03-08 10:07:52.647647"
  },
  {
    "title": "AOC AGON AG273QCX - WQHD HDR Curved Gaming Monitor (144 Hz)",
    "subtitle": "FreeSync 2 | In hoogte verstelbaar | USB-hub | Ingebouwde speakers | HDR400 |",
    "price": "517.53",
    "rating": "100%",
    "date": "2021-03-08 10:07:52.648639"
  },
  {
    "title": "LG 29UM58 - Full HD Monitor",
    "subtitle": "Game in UltraWide!",
    "price": "None",
    "rating": "94%",
    "date": "2021-03-08 10:07:52.649631"
  },
  {
    "title": "Denver MLC-3202G 80 cm (31.5\") 1920 x 1080 Pixels Full HD LED Zwart",
    "subtitle": null,
    "price": "319.00",
    "rating": null,
    "date": "2021-03-08 10:07:52.650623"
  },
  {
    "title": "AOC Gaming AG273QX computer monitor 68,6 cm (27\") 2560 x 1440 Pixels Quad HD LCD Zwart, Rood",
    "subtitle": null,
    "price": "546.85",
    "rating": null,
    "date": "2021-03-08 10:07:52.651615"
  },
  {
    "title": "AOC G2460FQ - Gaming Monitor",
    "subtitle": null,
    "price": "243.02",
    "rating": null,
    "date": "2021-03-08 10:07:52.652607"
  },
  {
    "title": "Benq XL2731 68,6 cm (27\") 1920 x 1080 Pixels Full HD LED Zwart",
    "subtitle": null,
    "price": "299.00",
    "rating": null,
    "date": "2021-03-08 10:07:52.653599"
  }
,
  {
    "title": "Acer Predator XB270HAbprz - Monitor",
    "subtitle": "Full HD Monitor",
    "price": "None",
    "rating": null,
    "date": "2021-03-08 10:07:53.106077"
  },
  {
    "title": "Iiyama ProLite E2783QSU - WQHD Monitor",
    "subtitle": "WQHD-monitor met snelle reactietijd van 1 ms, TN-paneel en FreeSync",
    "price": "None",
    "rating": "92%",
    "date": "2021-03-08 10:07:53.107069"
  },
  {
    "title": "AOC AG272FCX6 - Curved Gaming Monitor (165Hz)",
    "subtitle": "1ms Full HD in hoogte verstelbare curved gaming monitor met FreeSync",
    "price": "None",
    "rating": "80%",
    "date": "2021-03-08 10:07:53.108061"
  },
  {
    "title": "Acer XZ321QU - WQHD Curved Gaming Monitor (144 Hz)",
    "subtitle": "Met VA-paneel, FreeSync, ingebouwde speakers en is in hoogte verstelbaar",
    "price": "None",
    "rating": "96%",
    "date": "2021-03-08 10:07:53.109053"
  },
  {
    "title": "LG 27MK400H - Full HD TN Monitor - 27 inch",
    "subtitle": "27\" Full HD Monitor met FreeSync\u2122",
    "price": "180.46",
    "rating": "80%",
    "date": "2021-03-08 10:07:53.110045"
  },
  {
    "title": "Nitro XZ272UPbmiiphx - 27i QHD",
    "subtitle": null,
    "price": "359.00",
    "rating": null,
    "date": "2021-03-08 10:07:53.111037"
  },
  {
    "title": "iiyama G-MASTER GB2888UHSU - 4K Ultra HD Monitor",
    "subtitle": null,
    "price": "None",
    "rating": null,
    "date": "2021-03-08 10:07:53.112029"
  },
  {
    "title": "AOC AGON AG271QG - WQHD Gaming Monitor (165 Hz)",
    "subtitle": "Met G-Sync ondersteuning en een 4ms reactietijd",
    "price": "686.42",
    "rating": "88%",
    "date": "2021-03-08 10:07:53.113021"
  },
  {
    "title": "DELL S2719DGF 68,6 cm (27\") 2560 x 1440 Pixels Quad HD LCD Zilver",
    "subtitle": null,
    "price": "601.28",
    "rating": null,
    "date": "2021-03-08 10:07:53.114013"
  },
  {
    "title": "HP OMEN by HP 27 inch - Gaming Monitor",
    "subtitle": "De QHD-resolutie transformeert je content en zorgt voor een ultieme entertainmentervaring",
    "price": "899.00",
    "rating": null,
    "date": "2021-03-08 10:07:53.115005"
  },
  {
    "title": "Viewsonic Elite XG270 LED display 68,6 cm (27\") 1920 x 1080 Pixels Full HD Zwart",
    "subtitle": null,
    "price": "519.95",
    "rating": null,
    "date": "2021-03-08 10:07:53.115997"
  },
  {
    "title": "Iiyama ProLite E2591HSU-B1 - Gaming Monitor - 24.5 Inch (75Hz)",
    "subtitle": null,
    "price": "None",
    "rating": null,
    "date": "2021-03-08 10:07:53.117031"
  },
  {
    "title": "Dell U2419HC - Full HD IPS USB-C Monitor - 24 inch",
    "subtitle": null,
    "price": "None",
    "rating": null,
    "date": "2021-03-08 10:07:53.117485"
  },
  {
    "title": "ASUS VG279Q1R 68,6 cm (27\") 1920 x 1080 Pixels Full HD Zwart",
    "subtitle": null,
    "price": "302.95",
    "rating": null,
    "date": "2021-03-08 10:07:53.118477"
  },
  {
    "title": "Ozone DSP27 68,6 cm (27\") 1920 x 1080 Pixels Full HD LED Zwart",
    "subtitle": null,
    "price": "328.69",
    "rating": null,
    "date": "2021-03-08 10:07:53.119469"
  },
  {
    "title": "Acer CB CB281HK 71,1 cm (28\") 3840 x 2160 Pixels 4K Ultra HD LED Zwart",
    "subtitle": null,
    "price": "None",
    "rating": null,
    "date": "2021-03-08 10:07:53.120461"
  },
  {
    "title": "Acer XF XF240Q P 59,9 cm (23.6\") 1920 x 1080 Pixels Full HD LED Zwart",
    "subtitle": null,
    "price": "None",
    "rating": null,
    "date": "2021-03-08 10:07:53.121453"
  },
  {
    "title": "ASUS PB287Q - 28\" 4K ultra HD Monitor",
    "subtitle": "4K HD Monitor",
    "price": "None",
    "rating": "91%",
    "date": "2021-03-08 10:07:53.122445"
  }
]